torchgs/__init__.py
torchgs/grid_search.py
torchgs/metrics.py
torchgs/optimizers.py
torchgs/trainer.py
torchgs-0.0.2.dist-info/LICENSE
torchgs-0.0.2.dist-info/METADATA
torchgs-0.0.2.dist-info/WHEEL
torchgs-0.0.2.dist-info/top_level.txt
torchgs-0.0.2.dist-info/RECORD
