Metadata-Version: 2.1
Name: torchgs
Version: 0.0.2
Summary: Pytorch wrapper for performing grid-search
Home-page: https://github.com/danny-1k/torch-gs
Author: Daniel Ik
Author-email: codingeinstein@gmail.com
License: UNKNOWN
Keywords: pytorch,machine-learning,deep-learning,deep learning,machine learning,grid-search,grid search
Platform: UNKNOWN
Classifier: Intended Audience :: Developers
Classifier: Programming Language :: Python :: 3
Classifier: License :: OSI Approved :: MIT License
Classifier: Operating System :: OS Independent
Requires-Python: >=3.7
Requires-Dist: torch
Requires-Dist: tabulate
Requires-Dist: scikit-learn
